dbtool.py
dbtool-0.2.0.dist-info/LICENSE
dbtool-0.2.0.dist-info/WHEEL
dbtool-0.2.0.dist-info/METADATA
dbtool-0.2.0.dist-info/RECORD
