Metadata-Version: 2.1
Name: dbtool
Version: 0.2.0
Summary: A lightweight db tools for sql.
Author: Mario Luo
Author-email: luokaiqiongmou@foxmail.com
Requires-Python: >=3.6,<4.0
Classifier: License :: OSI Approved :: MIT License
Classifier: Operating System :: OS Independent
Classifier: Programming Language :: Python :: 3
Classifier: Programming Language :: Python :: 3.6
Classifier: Programming Language :: Python :: 3.7
Classifier: Programming Language :: Python :: 3.8
Classifier: Programming Language :: Python :: 3.9
Classifier: Programming Language :: Python :: 3.10
Classifier: Programming Language :: Python :: 3.11
Classifier: Programming Language :: Python :: 3
Requires-Dist: dbutils
Project-URL: Bug Tracker, https://github.com/lkqm/dbtool.py/issues
Project-URL: Homepage, https://github.com/lkqm/dbtool.py
